configfactory/__init__.py
configfactory/auth.py
configfactory/backup.py
configfactory/context_processors.py
configfactory/decorators.py
configfactory/exceptions.py
configfactory/forms.py
configfactory/logs.py
configfactory/middleware.py
configfactory/models.py
configfactory/paths.py
configfactory/runner.py
configfactory/scheduler.py
configfactory/services.py
configfactory/settings.py
configfactory/urls.py
configfactory/utils.py
configfactory/views.py
configfactory/wsgi.py
configfactory/api/__init__.py
configfactory/api/urls.py
configfactory/api/views.py
configfactory/auth/__init__.py
configfactory/auth/base.py
configfactory/auth/context_processors.py
configfactory/auth/decorators.py
configfactory/auth/forms.py
configfactory/auth/middleware.py
configfactory/auth/models.py
configfactory/auth/urls.py
configfactory/auth/utils.py
configfactory/auth/views.py
configfactory/config/__init__.py
configfactory/config/base.py
configfactory/config/backends/__init__.py
configfactory/config/backends/base.py
configfactory/config/backends/database.py
configfactory/config/backends/file.py
configfactory/config/backends/memory.py
configfactory/configurations/__init__.py
configfactory/configurations/apps.py
configfactory/configurations/config.py
configfactory/configurations/context_processors.py
configfactory/configurations/forms.py
configfactory/configurations/settings.py
configfactory/configurations/urls.py
configfactory/configurations/views.py
configfactory/configurations/backends/__init__.py
configfactory/configurations/backends/base.py
configfactory/configurations/backends/database.py
configfactory/configurations/backends/file.py
configfactory/configurations/backends/memory.py
configfactory/environments/__init__.py
configfactory/environments/apps.py
configfactory/environments/helpers.py
configfactory/environments/management.py
configfactory/environments/managers.py
configfactory/environments/models.py
configfactory-0.35.dev0.dist-info/DESCRIPTION.rst
configfactory-0.35.dev0.dist-info/METADATA
configfactory-0.35.dev0.dist-info/RECORD
configfactory-0.35.dev0.dist-info/WHEEL
configfactory-0.35.dev0.dist-info/entry_points.txt
configfactory-0.35.dev0.dist-info/metadata.json
configfactory-0.35.dev0.dist-info/top_level.txt
